bifidoannotator/__init__.py
bifidoannotator/cli.py
bifidoannotator/data/mapping_file.txt
bifidoannotator/database/mapping_file.tsv
bifidoannotator-1.0.2.dist-info/licenses/LICENSE
bifidoannotator-1.0.2.dist-info/METADATA
bifidoannotator-1.0.2.dist-info/WHEEL
bifidoannotator-1.0.2.dist-info/entry_points.txt
bifidoannotator-1.0.2.dist-info/top_level.txt
bifidoannotator-1.0.2.dist-info/RECORD
